zbricklib_auth/__init__.py
zbricklib_auth/py.typed
zbricklib_auth-0.1.0.dist-info/METADATA
zbricklib_auth-0.1.0.dist-info/WHEEL
zbricklib_auth-0.1.0.dist-info/RECORD
