Metadata-Version: 2.1
Name: zbricklib-auth
Version: 0.1.0
Summary: Authentication system for zbricklib
Author: zdeyn
Author-email: zdeyn@zdeyn.com
Requires-Python: >=3.10,<4.0
Classifier: Programming Language :: Python :: 3
Classifier: Programming Language :: Python :: 3.10
Classifier: Programming Language :: Python :: 3.11
Classifier: Programming Language :: Python :: 3.12
Requires-Dist: zbricklib (>=0.1.1,<0.2.0)
